[
  {
    "url": "https://www.boat-lifestyle.com/pages/return-policy",
    "category": "Return Policy",
    "raw_content": "boAt - Return Policy\nOpen Modal\n×\nSkip to content\nGet additional 5% off on Prepaid Orders | Code:\nPAYDAY |\nShop Now!\nGet additional 5% off on Prepaid Orders | Code:\nBOATHEAD\n|\nShop Now\nCategories\nboAt Personalisation\nCorporate Orders\nGifting Store\nMore\nNavigation\nboAt Lifestyle\nNewsletter\nSearch\nMost Searched & Bought\nMost Searched And Bought\nTrue Wireless\nEarphones\nPersonalized\nProducts\nSmart\nWatches\nNirvana\nWireless\nNeckbands\nBluetooth\nSpeakers\nWireless\nHeadphones\nPowerbanks\nWired\nEarphones\nSoundbars\nTrimmers\n×\nHi boAthead!\nLogin\n0\nSearch\nMost Searched & Bought\nMost Searched And Bought\nTrue Wireless\nEarphones\nPersonalized\nProducts\nSmart\nWatches\nNirvana\nWireless\nNeckbands\nBluetooth\nSpeakers\nWireless\nHeadphones\nPowerbanks\nWired\nEarphones\nSoundbars\nTrimmers\nCategories\nTrue Wireless Earbuds\nPersonalised Products\nNeckbands\nSmart Watches\nWireless Headphones\nWireless Speakers\nWired Headphones\nWired Earphones\nSoundbars\nGaming Headphones\nParty Speakers\nChargers\nPower Banks\nCables\nSuperhero Collection\nTrebel for Women\nLimited Edition\nBoAt Tag\nMobile Accessories\nExpand More\nBack\nView All\nboAt Personalisation\nCorporate Orders\nGifting Store\nMore\nDaily Deals\nBlogs\nRefer & Earn\nCareers\nSocial Responsibility\nStore Locator\nboAt Community\nBack\nView All\nTrack Your Order\nYour Cart\nYour cart is feeling lonely\nStart shopping\nReturn Policy\nReplacement Policy\nReplacement of a product is allowed only under the following circumstances:\nThe customer can replace the product unit received within 7 days from the date of delivery and get a replacement unit delivered to the customer.\nReplacement can be made if the customer establishes that the product delivered in defective condition or has a physical damage within 24 hours of receipt of the product\nReplacement with a fresh box unit can be provided to the customer if the customer establishes that the product delivered is not functioning properly within 7 days from the date of delivery.\nIn case of receipt of damaged or defective items please report the same to our website support team. The request will, however, be entertained once a boAt team member has checked and determined the same at his own end. This is typically reported back to the customer within 24 hours of receipt of the products by boAt.\nIn case you feel that the product received is not as shown on the site or as per the specifications, you must bring it to the notice of our website support team within 24 hours of receiving the product. The website support team after looking into your complaint will take an appropriate decision.\nIn case of replacement, the whole product package with the product and its accessories intact will be picked up by the courier boy arranged by us.\nA product will not be replaced under the following circumstances:\nCustomer is not happy with the look/sound quality of a defect free product\nPhysical damage not notified within 24 hours of receiving the product\nAn electrical surge or any damage caused by the user.\nPlease see that no return or refund shall be provided. However, the customer can replace the product unit received within 7 days from the date of delivery and get a replacement.\nCancellation Policy\nWe believe in helping our customers as far as possible, and has therefore a liberal cancellation policy. However, under this policy:\nCancellations request will not be entertained if the orders have already been communicated to the customers and they have initiated the process of shipping them.\nThere is no cancellation of orders placed under the Same Day Delivery category.\nNo cancellations are entertained for those products that have been obtained on special occasions. (These are limited occasion offers and therefore cancellations are not possible.)\nProduct Pricing\nProduct prices listed on the website are current. While every care has been taken to label the products accurately, errors in data entry and updating may occur. We reserve the right to cancel the order incase a transaction has been made where the price indicated was not the correct price. In the rare event that happens, we will give a full refund of all money received from the customer.\nPrices are subject to change without advance notice.\nAll prices on this web site in Indian Rupees. For international cards used on the site, the banks applicable exchange rate and charges will apply. We have no jurisdiction on this and any disputes or queries on exchange rates and bank charges need to be directed to the bank or institution that issued your card or payment instrument\nAll orders are acknowledged at current pricing. We will bill at price in effect at the time of receipt of money and raising of an invoice.\nOur products are liable for GST in India.\nSecurity\nTransactions on the website are protected by SSL (Secure Sockets Layer) and Secure Data Encryption using a 1024-bit process. Any information you enter when transacting with the webstore is sent in a Secure Socket Layer (SSL) session and is encrypted to protect you against unintentional disclosure to third parties. This is an assurance that it follows the best security practices adopted by major online vendors where all payments are processed in real-time for your security and immediate peace of mind.\nCredit card and Debit card information is not stored by us and is not taken by us. This information is taken directly by the payment gateway provided who is authorised and is compliant with the regulations and requirements of various banks and institutions and payment franchisees that it is associated with.\nTo report security vulnerabilities affecting any of our products send an email to info@imaginemarketingindia.com.\nOut of Stock situations\nOur endeavour is to ensure that all products listed on the site are available in stock for dispatch to the buyer. However, in case the same is not available for any reason, we are liable to process the refund.\nDelivery of products\nPurchases are shipped from our own or third-party warehouses/ stores or offices from various points in India. Our endeavor is to make the products reach you within 7-10 Business days from receipt of order and payment depending on the address for delivery.\nOrder deliveries will be made by our own staff or third-party courier and logistics companies or Postal Services usually between 10.30 am – 7 pm Monday –Saturday.\nGoods will need to be signed for upon delivery. We take no responsibility for goods signed by an alternative person other than the person ordering the product at the address indicated at the time of the order.\nSince the transactions are authorised by the card holder, we do not take responsibility for incorrect addresses provided at the time of placing the order\nWe are not responsible for damage of products after delivery.\nAll claims, if any, for shortages or damages must be reported to customer service on the day of delivery through the contact us page on the web store. Also, the said shortage of goods needs be highlighted and signed on the Proof of delivery copy and returned to the delivery person.\nIn case your order has not been delivered but is reflecting “Delivered” on the tracker, please highlight it within 24 hours or else we will not be able to process your request.\nIf a product is undelivered or returned to its origin, customers are entitled to receive a full refund. This condition is applicable only on products without any custom engraving.\nDelivery Charges\nShipping and handling rates may vary based on product, packaging, size, volume, type and other considerations. The shipping and handling charges are given at the time of check out and consumers will know about this before making payments.\nShipping charges Rs 30 levied on orders below Rs 499.\nBack to top\nIndia's fastest growing audio & wearables brand. The most incredible range of\nwireless earphones\n,\nearbuds\n,\nheadphones\n,\nsmart watches\n, and\nhome audio\n. From workouts to adventures, boAt\nwill get you sailing!\nSubscribe to our email alerts!\nShop\nTrue Wireless Earbuds\nWireless Headphones\nWired Headphones\nWireless Speakers\nHome Audio\nMobile Accessories\nSmart Watches\nTRebel\nMisfit Trimmers\nRefer & Earn\nHelp\nTrack Your Order\nWarranty & Support\nReturn Policy\nService Centers\nBulk Orders\nWhy Buy Direct\nCompany\nAbout boAt\nNews\nRead Our Blog\nCareers\nSecurity\nInvestor Relations\nSocial Responsibility\nShop\nTrue Wireless Earbuds\nWireless Headphones\nWired Headphones\nWireless Speakers\nHome Audio\nMobile Accessories\nSmart Watches\nTRebel\nMisfit Trimmers\nRefer & Earn\nHelp\nTrack Your Order\nWarranty & Support\nReturn Policy\nService Centers\nBulk Orders\nWhy Buy Direct\nCompany\nAbout boAt\nNews\nRead Our Blog\nCareers\nSecurity\nInvestor Relations\nSocial Responsibility\nTrue Wireless Earbuds\nShop by Features\nNoise Cancellation Earbuds\nGaming Earbuds\nLarge Playback Earbuds\nShop by Price\nEarbuds Under 1000\nEarbuds Under 2000\nEarbuds Under 3000\nEarbuds Under 4000\nEarbuds Under 5000\nWireless Earphones\nShop by Features\nNoise Cancellation Earphone\nLong Playback Earphone\nClear Calling Earphone\nShop by Price\nNeckbands Under 1000\nNeckbands Under 2000\nNeckbands Under 3000\nWired Earphones\nShop by Features\nWired Headphones with Mic\nWired Headphones with Mic\nHeadphones with Mic for PC\nShop by Price\nWired Headphones Under 1000\nWired Headphones Under 2000\nWired Headphones Under 3000\nGaming Headphones\nShop by Features\nGaming Headphones with Mic\nLow Latency Headphone\nRGB Light Headphones\nHeadphone for PC Gaming\nWireless Speakers\nShop by Features\nPortable Speakers\nLong Playback Speakers\nWaterproof Bluetooth Speaker\nParty Speaker with RGB Lights\nSpeaker with Karaoke Mic\nShop by Price\nBluetooth Speakers Under 1000\nBluetooth Speakers Under 2000\nBluetooth Speakers Under 3000\nBluetooth Speakers Under 5000\nBluetooth Speakers Under 8000\nSoundbars\nShop by Features\nSoundbar with Wireless Subwoofer\nDolby Soundbars\nSoundbar with Wired Subwoofer\nAlexa Enabled Soundbar\nShop by Price\nSoundbars Under 10000\nSoundbars Under 20000\nSoundbars Under 3000\nSoundbars Under 5000\nSoundbars Above 20000\nSmart Watches\nShop by Features\nBluetooth Calling Smartwatches\nFitness Tracker Smartwatch\nBig Display Smartwatch\nSports Tracker Smartwatch\nShop by Identity\nSmartwatches For Women/Girls\nSmartwatches For Men/Boys\nShop by Price\nSmartwatch Under 1000\nSmartwatch Under 2000\nSmartwatch Under 3000\nSmartwatch Under 4000\nSmartwatch Under 5000\nSmartwatch Above 5000\nTrimmers\nShop by Features\nTrimmer for Men\nTrimmers with Grooming Kit for Men\nShop by Price\nTrimmer Under 1000\nTrimmer Under 2000\nLimited Editions\nShop by Features\nLimited Editions Headphones\nLimited Editions Earphone\nLimited Edition Speakers\nCar Accessories\nShop by Features\nAux Cable for Car\nShop by Price\nCar Charger Under 500\nCar Charger Above 500\nTrebel Range\nShop by Features\nEarbuds for Women\nPowerbanks\nShop by Features\nPower Bank 10000mah\nPower Bank 20000mah\nMobile Power Bank\nFast Charging Power Bank\nPower Bank for iPhone\nShop by Price\nPower Bank Under 1000\nPower Bank Under 1500\nPower Bank Under 2000\nChargers\nShop by Features\nWireless Charger\nType C Charger\nFast Charger\nUSB Charger\nMicro USB Charger\nType C Adapter\nCables\nShop by Features\nMicro USB Cable\nC Type Cable\nLightning Cable\nUSB C to C Cable\nSmart Watch Charging Cable\nWireless Headphones\nShop by Features\nNoise Cancelling Headphones\nWireless Gaming Headphone\nLong Playback Headphones\nShop by Price\nWireless Headphones Under 1000\nWireless Headphones Under 3000\nWireless Headphones Under 2000\nWireless Headphones Under 4000\nWireless Headphones Above 4000\nWired Headphones\nShop by Features\nWired Headphones with Mic\nWired Headphones with Mic\nHeadphones with Mic for PC\nShop by Price\nWired Headphones Under 1000\nWired Headphones Under 2000\nWired Headphones Under 3000\nLet's get social\nLet's get social\nPrivacy Policy\nTerms of Use\nWarranty Policy\n© 2025 Imagine Marketing Limited. All Rights Reserved.\nFor queries contact us:\nManager, Imagine Marketing Limited\nUnit no. 204 & 205, 2nd floor, D-wing & E-wing,\nCorporate Avenue, Andheri Ghatkopar Link Road,\nMumbai, Maharashtra-400093, India\nHome\nCategories\nRewards\nPersonalisation\nChat",
    "structured_content": {
      "replacement_timeframe": 7,
      "replacement_conditions": [
        "Product received is defective",
        "Product has physical damage (reported within 24 hours of receipt)",
        "Product is not functioning properly (within 7 days of delivery)",
        "Product received is not as shown on the site or as per specifications (reported within 24 hours of receipt)"
      ],
      "non_replacement_conditions": [
        "Customer is unhappy with the look/sound quality of a defect-free product",
        "Physical damage not notified within 24 hours of receiving the product",
        "Damage caused by an electrical surge or user error"
      ],
      "cancellation_conditions": [
        "Orders already communicated to the customer and shipping initiated",
        "Orders placed under Same Day Delivery",
        "Products obtained on special occasions (limited occasion offers)"
      ],
      "return_policy_summary": "Replacements are allowed within 7 days of delivery for defective or damaged products, or if the product doesn't match the website description.  Replacements are not allowed for issues with look/sound quality or user-caused damage. Cancellations are generally not allowed after shipping has begun, for same-day deliveries, or for special occasion purchases.  Refunds are not provided, but a replacement may be offered within the timeframe."
    }
  },
  {
    "url": "https://www.boat-lifestyle.com/pages/service-center-list",
    "category": "Service Centers",
    "raw_content": "#1 Customer Support - boAt Service Center List\nOpen Modal\n×\nSkip to content\nGet additional 5% off on Prepaid Orders | Code:\nPAYDAY |\nShop Now!\nGet additional 5% off on Prepaid Orders | Code:\nBOATHEAD\n|\nShop Now\nCategories\nboAt Personalisation\nCorporate Orders\nGifting Store\nMore\nNavigation\nboAt Lifestyle\nNewsletter\nSearch\nMost Searched & Bought\nMost Searched And Bought\nTrue Wireless\nEarphones\nPersonalized\nProducts\nSmart\nWatches\nNirvana\nWireless\nNeckbands\nBluetooth\nSpeakers\nWireless\nHeadphones\nPowerbanks\nWired\nEarphones\nSoundbars\nTrimmers\n×\nHi boAthead!\nLogin\n0\nSearch\nMost Searched & Bought\nMost Searched And Bought\nTrue Wireless\nEarphones\nPersonalized\nProducts\nSmart\nWatches\nNirvana\nWireless\nNeckbands\nBluetooth\nSpeakers\nWireless\nHeadphones\nPowerbanks\nWired\nEarphones\nSoundbars\nTrimmers\nCategories\nTrue Wireless Earbuds\nPersonalised Products\nNeckbands\nSmart Watches\nWireless Headphones\nWireless Speakers\nWired Headphones\nWired Earphones\nSoundbars\nGaming Headphones\nParty Speakers\nChargers\nPower Banks\nCables\nSuperhero Collection\nTrebel for Women\nLimited Edition\nBoAt Tag\nMobile Accessories\nExpand More\nBack\nView All\nboAt Personalisation\nCorporate Orders\nGifting Store\nMore\nDaily Deals\nBlogs\nRefer & Earn\nCareers\nSocial Responsibility\nStore Locator\nboAt Community\nBack\nView All\nTrack Your Order\nYour Cart\nYour cart is feeling lonely\nStart shopping\nDelhi NCR\nPunjab\nUttar Pradesh\nWest Bengal\nHaryana\nBihar\nGujarat\nRajasthan\nJammu & Kashmir\nMaharashtra\nAssam\nTelangana\nKarnataka\nTamil Nadu\nKerala\nJharkhand\nOdisha\nMadhya Pradesh\nAndhra Pradesh\nUttarakhand\nChhattisgarh\nPlease Note:\nService centers will remain shut on Sundays and National holidays.\nImage with text block\nSubheading\nUse block text to give your customers insight into your brand. Select impactful text that relates to your brand and story.\nBack to top\nIndia's fastest growing audio & wearables brand. The most incredible range of\nwireless earphones\n,\nearbuds\n,\nheadphones\n,\nsmart watches\n, and\nhome audio\n. From workouts to adventures, boAt\nwill get you sailing!\nSubscribe to our email alerts!\nShop\nTrue Wireless Earbuds\nWireless Headphones\nWired Headphones\nWireless Speakers\nHome Audio\nMobile Accessories\nSmart Watches\nTRebel\nMisfit Trimmers\nRefer & Earn\nHelp\nTrack Your Order\nWarranty & Support\nReturn Policy\nService Centers\nBulk Orders\nWhy Buy Direct\nCompany\nAbout boAt\nNews\nRead Our Blog\nCareers\nSecurity\nInvestor Relations\nSocial Responsibility\nShop\nTrue Wireless Earbuds\nWireless Headphones\nWired Headphones\nWireless Speakers\nHome Audio\nMobile Accessories\nSmart Watches\nTRebel\nMisfit Trimmers\nRefer & Earn\nHelp\nTrack Your Order\nWarranty & Support\nReturn Policy\nService Centers\nBulk Orders\nWhy Buy Direct\nCompany\nAbout boAt\nNews\nRead Our Blog\nCareers\nSecurity\nInvestor Relations\nSocial Responsibility\nTrue Wireless Earbuds\nShop by Features\nNoise Cancellation Earbuds\nGaming Earbuds\nLarge Playback Earbuds\nShop by Price\nEarbuds Under 1000\nEarbuds Under 2000\nEarbuds Under 3000\nEarbuds Under 4000\nEarbuds Under 5000\nWireless Earphones\nShop by Features\nNoise Cancellation Earphone\nLong Playback Earphone\nClear Calling Earphone\nShop by Price\nNeckbands Under 1000\nNeckbands Under 2000\nNeckbands Under 3000\nWired Earphones\nShop by Features\nWired Headphones with Mic\nWired Headphones with Mic\nHeadphones with Mic for PC\nShop by Price\nWired Headphones Under 1000\nWired Headphones Under 2000\nWired Headphones Under 3000\nGaming Headphones\nShop by Features\nGaming Headphones with Mic\nLow Latency Headphone\nRGB Light Headphones\nHeadphone for PC Gaming\nWireless Speakers\nShop by Features\nPortable Speakers\nLong Playback Speakers\nWaterproof Bluetooth Speaker\nParty Speaker with RGB Lights\nSpeaker with Karaoke Mic\nShop by Price\nBluetooth Speakers Under 1000\nBluetooth Speakers Under 2000\nBluetooth Speakers Under 3000\nBluetooth Speakers Under 5000\nBluetooth Speakers Under 8000\nSoundbars\nShop by Features\nSoundbar with Wireless Subwoofer\nDolby Soundbars\nSoundbar with Wired Subwoofer\nAlexa Enabled Soundbar\nShop by Price\nSoundbars Under 10000\nSoundbars Under 20000\nSoundbars Under 3000\nSoundbars Under 5000\nSoundbars Above 20000\nSmart Watches\nShop by Features\nBluetooth Calling Smartwatches\nFitness Tracker Smartwatch\nBig Display Smartwatch\nSports Tracker Smartwatch\nShop by Identity\nSmartwatches For Women/Girls\nSmartwatches For Men/Boys\nShop by Price\nSmartwatch Under 1000\nSmartwatch Under 2000\nSmartwatch Under 3000\nSmartwatch Under 4000\nSmartwatch Under 5000\nSmartwatch Above 5000\nTrimmers\nShop by Features\nTrimmer for Men\nTrimmers with Grooming Kit for Men\nShop by Price\nTrimmer Under 1000\nTrimmer Under 2000\nLimited Editions\nShop by Features\nLimited Editions Headphones\nLimited Editions Earphone\nLimited Edition Speakers\nCar Accessories\nShop by Features\nAux Cable for Car\nShop by Price\nCar Charger Under 500\nCar Charger Above 500\nTrebel Range\nShop by Features\nEarbuds for Women\nPowerbanks\nShop by Features\nPower Bank 10000mah\nPower Bank 20000mah\nMobile Power Bank\nFast Charging Power Bank\nPower Bank for iPhone\nShop by Price\nPower Bank Under 1000\nPower Bank Under 1500\nPower Bank Under 2000\nChargers\nShop by Features\nWireless Charger\nType C Charger\nFast Charger\nUSB Charger\nMicro USB Charger\nType C Adapter\nCables\nShop by Features\nMicro USB Cable\nC Type Cable\nLightning Cable\nUSB C to C Cable\nSmart Watch Charging Cable\nWireless Headphones\nShop by Features\nNoise Cancelling Headphones\nWireless Gaming Headphone\nLong Playback Headphones\nShop by Price\nWireless Headphones Under 1000\nWireless Headphones Under 3000\nWireless Headphones Under 2000\nWireless Headphones Under 4000\nWireless Headphones Above 4000\nWired Headphones\nShop by Features\nWired Headphones with Mic\nWired Headphones with Mic\nHeadphones with Mic for PC\nShop by Price\nWired Headphones Under 1000\nWired Headphones Under 2000\nWired Headphones Under 3000\nLet's get social\nLet's get social\nPrivacy Policy\nTerms of Use\nWarranty Policy\n© 2025 Imagine Marketing Limited. All Rights Reserved.\nFor queries contact us:\nManager, Imagine Marketing Limited\nUnit no. 204 & 205, 2nd floor, D-wing & E-wing,\nCorporate Avenue, Andheri Ghatkopar Link Road,\nMumbai, Maharashtra-400093, India\nHome\nCategories\nRewards\nPersonalisation\nChat",
    "structured_content": {
      "states_with_centers": [
        "Delhi NCR",
        "Punjab",
        "Uttar Pradesh",
        "West Bengal",
        "Haryana",
        "Bihar",
        "Gujarat",
        "Rajasthan",
        "Jammu & Kashmir",
        "Maharashtra",
        "Assam",
        "Telangana",
        "Karnataka",
        "Tamil Nadu",
        "Kerala",
        "Jharkhand",
        "Odisha",
        "Madhya Pradesh",
        "Andhra Pradesh",
        "Uttarakhand",
        "Chhattisgarh"
      ],
      "service_hours": null,
      "holiday_info": "Service centers will remain shut on Sundays and National holidays.",
      "contact_details": {
        "address": "Unit no. 204 & 205, 2nd floor, D-wing & E-wing, Corporate Avenue, Andheri Ghatkopar Link Road, Mumbai, Maharashtra-400093, India",
        "name": "Manager, Imagine Marketing Limited"
      }
    }
  }
]